grassnechik/__init__.py
grassnechik/constants.py
grassnechik/grassnechik.py
grassnechik/key.py
grassnechik/types.py
grassnechik-0.3.1.dist-info/LICENSE
grassnechik-0.3.1.dist-info/METADATA
grassnechik-0.3.1.dist-info/WHEEL
grassnechik-0.3.1.dist-info/RECORD
