Metadata-Version: 2.1
Name: grassnechik
Version: 0.3.1
Summary: Cryptography Library
Author: Sviatoslav Bobryshev
Author-email: wstswsb@gmail.com
Requires-Python: >=3.12,<4.0
Classifier: Programming Language :: Python :: 3
Classifier: Programming Language :: Python :: 3.12
